dribbble_py/__init__.py
dribbble_py/cli.py
dribbble_py/dribbble_user.py
dribbble_py/silent_selector.py
dribbble_py/utils.py
dribbble_py-0.0.1.dist-info/LICENSE
dribbble_py-0.0.1.dist-info/METADATA
dribbble_py-0.0.1.dist-info/WHEEL
dribbble_py-0.0.1.dist-info/entry_points.txt
dribbble_py-0.0.1.dist-info/top_level.txt
dribbble_py-0.0.1.dist-info/RECORD
