Metadata-Version: 2.1
Name: dribbble-py
Version: 0.0.1
Summary: Dribbble Downloader
Home-page: https://github.com/rand-net/dribbble-py
Author: rand-net
License: MIT
Keywords: dribbble,dribbble-scraper,scraper,graphic-design,design
Platform: UNKNOWN
Classifier: License :: OSI Approved :: MIT License
Classifier: Programming Language :: Python :: 3
Classifier: Programming Language :: Python :: 3.8
License-File: LICENSE
Requires-Dist: art
Requires-Dist: beautifulsoup4
Requires-Dist: chompjs
Requires-Dist: requests
Requires-Dist: lxml
Requires-Dist: httpx
Requires-Dist: trio
